pycg_external_module/__init__.py
pycg_external_module/ext.py
pycg_external_module-1.1.dist-info/LICENSE
pycg_external_module-1.1.dist-info/METADATA
pycg_external_module-1.1.dist-info/WHEEL
pycg_external_module-1.1.dist-info/top_level.txt
pycg_external_module-1.1.dist-info/RECORD
