Metadata-Version: 2.1
Name: pycg-external-module
Version: 1.1
Summary: External module for PyCG micro-benchmark
Home-page: UNKNOWN
Author: Ashwin Prasad
Author-email: ashwin.prasad@upb.de
License: GPL-3.0
Platform: UNKNOWN
